original_janken.py
original_janken-0.0.2.dist-info/LICENSE.txt
original_janken-0.0.2.dist-info/METADATA
original_janken-0.0.2.dist-info/WHEEL
original_janken-0.0.2.dist-info/entry_points.txt
original_janken-0.0.2.dist-info/top_level.txt
original_janken-0.0.2.dist-info/RECORD
